batchstats/__init__.py
batchstats/_misc.py
batchstats/base/__init__.py
batchstats/base/batch_nan_stat.py
batchstats/base/batch_stat.py
batchstats/nanstats/__init__.py
batchstats/nanstats/nan_max.py
batchstats/nanstats/nan_mean.py
batchstats/nanstats/nan_min.py
batchstats/nanstats/nan_peak_to_peak.py
batchstats/nanstats/nan_sum.py
batchstats/stats/__init__.py
batchstats/stats/cov.py
batchstats/stats/max.py
batchstats/stats/mean.py
batchstats/stats/min.py
batchstats/stats/peak_to_peak.py
batchstats/stats/std.py
batchstats/stats/sum.py
batchstats/stats/var.py
batchstats-0.5.2.dist-info/licenses/LICENSE
batchstats-0.5.2.dist-info/METADATA
batchstats-0.5.2.dist-info/WHEEL
batchstats-0.5.2.dist-info/top_level.txt
batchstats-0.5.2.dist-info/RECORD
