Metadata-Version: 2.4
Name: batchstats
Version: 0.5.2
Summary: Efficient batch statistics computation library for Python.
Author: Cyril Joly
Project-URL: Homepage, https://github.com/CyrilJl/BatchStats
Classifier: Programming Language :: Python :: 3
Classifier: License :: OSI Approved :: MIT License
Classifier: Operating System :: OS Independent
Requires-Python: >=3.6
License-File: LICENSE
Requires-Dist: numpy
Dynamic: license-file
